abel/__init__.py
abel/linalg/__init__.py
abel/linalg/test_vector.py
abel/linalg/vector.py
abel-0.0.6.dist-info/METADATA
abel-0.0.6.dist-info/RECORD
abel-0.0.6.dist-info/WHEEL
abel-0.0.6.dist-info/top_level.txt
