Metadata-Version: 2.1
Name: abel
Version: 0.0.6
Summary: Machine learning components
Home-page: https://github.com/hunan-rostomyan/abel
Author: Hunan Rostomyan
Author-email: hunan131@gmail.com
License: BSD 3-clause
Platform: UNKNOWN
Classifier: Programming Language :: Python :: 3
Classifier: License :: OSI Approved :: BSD License
Classifier: Operating System :: OS Independent
